data_structures/__init__.py
data_structures/array_.py
data_structures/graph.py
data_structures/linked_list.py
data_structures/my_queue.py
data_structures/stack.py
data_structures/tree.py
python_basic_data_structures-0.0.1.dist-info/LICENSE
python_basic_data_structures-0.0.1.dist-info/METADATA
python_basic_data_structures-0.0.1.dist-info/WHEEL
python_basic_data_structures-0.0.1.dist-info/top_level.txt
python_basic_data_structures-0.0.1.dist-info/RECORD
